python_steam_api-2.2.1.dist-info/licenses/LICENCE
steam_web_api/__init__.py
steam_web_api/_version.py
steam_web_api/apps.py
steam_web_api/client.py
steam_web_api/constants.py
steam_web_api/steam.py
steam_web_api/steam_types.py
steam_web_api/users.py
steam_web_api/utils.py
python_steam_api-2.2.1.dist-info/METADATA
python_steam_api-2.2.1.dist-info/WHEEL
python_steam_api-2.2.1.dist-info/top_level.txt
python_steam_api-2.2.1.dist-info/RECORD
