Metadata-Version: 2.4
Name: python-steam-api
Version: 2.2.1
Summary: Python Client wrapper for Steam API.
Author-email: David Salazar <david.asal@hotmail.com>
Maintainer-email: Mathieu Scheltienne <mathieu.scheltienne@fcbg.ch>
Project-URL: source, https://github.com/deivit24/python-steam-api
Project-URL: tracker, https://github.com/deivit24/python-steam-api/issues
Keywords: api,python,steam community,steam,steamapi
Classifier: Development Status :: 4 - Beta
Classifier: Intended Audience :: Developers
Classifier: License :: OSI Approved :: MIT License
Classifier: Operating System :: OS Independent
Classifier: Programming Language :: Python :: 3 :: Only
Classifier: Programming Language :: Python :: 3.10
Classifier: Programming Language :: Python :: 3.11
Classifier: Programming Language :: Python :: 3.12
Classifier: Programming Language :: Python :: 3.9
Requires-Python: >=3.9
License-File: LICENCE
Requires-Dist: beautifulsoup4
Requires-Dist: requests
Provides-Extra: all
Requires-Dist: python-steam-api[build]; extra == "all"
Requires-Dist: python-steam-api[style]; extra == "all"
Provides-Extra: build
Requires-Dist: build; extra == "build"
Requires-Dist: twine; extra == "build"
Provides-Extra: full
Requires-Dist: python-steam-api[all]; extra == "full"
Provides-Extra: style
Requires-Dist: codespell[toml]>=2.2.4; extra == "style"
Requires-Dist: isort; extra == "style"
Requires-Dist: ruff>=0.1.8; extra == "style"
Requires-Dist: toml-sort; extra == "style"
Requires-Dist: yamllint; extra == "style"
Dynamic: license-file
